sfkit/api.py
sfkit/auth/auth.py
sfkit/auth/setup_networking.py
sfkit/cli.py
sfkit/encryption/generate_personal_keys.py
sfkit/encryption/mpc/encrypt_data.py
sfkit/encryption/mpc/encrypted_data/.placeholder
sfkit/encryption/mpc/random_number_generator.py
sfkit/encryption/mpc/test_data/input_data/cov.txt
sfkit/encryption/mpc/test_data/input_data/geno.txt
sfkit/encryption/mpc/test_data/input_data/pheno.txt
sfkit/encryption/mpc/test_data/input_data/pos.txt
sfkit/encryption/mpc/test_data/input_data1/cov.txt
sfkit/encryption/mpc/test_data/input_data1/geno.txt
sfkit/encryption/mpc/test_data/input_data1/pheno.txt
sfkit/encryption/mpc/test_data/input_data1/pos.txt
sfkit/encryption/mpc/test_data/input_data2/cov.txt
sfkit/encryption/mpc/test_data/input_data2/geno.txt
sfkit/encryption/mpc/test_data/input_data2/pheno.txt
sfkit/encryption/mpc/test_data/input_data2/pos.txt
sfkit/parser.py
sfkit/protocol/register_data.py
sfkit/protocol/run_protocol.py
sfkit/sidecar/client.py
sfkit/sidecar/server.py
sfkit/sidecar/utils.py
sfkit/utils/constants.py
sfkit/utils/dti_protocol.py
sfkit/utils/gwas_protocol.py
sfkit/utils/helper_functions.py
sfkit/utils/pca_protocol.py
sfkit/utils/sfgwas_helper_functions.py
sfkit/utils/sfgwas_lmm_protocol.py
sfkit/utils/sfgwas_protocol.py
sfkit/utils/sfrelate_protocol.py
sfkit-0.0.262.dist-info/METADATA
sfkit-0.0.262.dist-info/WHEEL
sfkit-0.0.262.dist-info/entry_points.txt
sfkit-0.0.262.dist-info/licenses/LICENSE
sfkit-0.0.262.dist-info/RECORD
