Metadata-Version: 2.4
Name: sfkit
Version: 0.0.262
Summary: Some CLI Tools For The Secure Multi-party Genomic Analysis Website
License-File: LICENSE
Author: Simon Mendelsohn
Author-email: smendels@broadinstitute.org
Requires-Python: >=3.10,<4.0
Classifier: License :: OSI Approved :: MIT License
Classifier: Operating System :: OS Independent
Classifier: Programming Language :: Python :: 3
Classifier: Programming Language :: Python :: 3.10
Classifier: Programming Language :: Python :: 3.11
Classifier: Programming Language :: Python :: 3.12
Classifier: Programming Language :: Python :: 3.13
Classifier: Programming Language :: Python :: 3.14
Requires-Dist: PyNaCl (>=1.5.0,<2.0.0)
Requires-Dist: checksumdir (>=1.2.0,<2.0.0)
Requires-Dist: google-auth (>=2.23.4,<3.0.0)
Requires-Dist: google-cloud-storage (>=2.13.0,<3.0.0)
Requires-Dist: joblib (>=1.3.2,<2.0.0)
Requires-Dist: matplotlib (>=3.10.3,<4.0.0)
Requires-Dist: numpy (>=1.26.1,<2.0.0)
Requires-Dist: pandas (>=2.1.2,<3.0.0)
Requires-Dist: pgenlib (>=0.90.2,<0.91.0)
Requires-Dist: pillow (>=11.3.0,<12.0.0)
Requires-Dist: pystun3 (>=2.0.0,<3.0.0)
Requires-Dist: qmplot (>=0.3.2,<0.4.0)
Requires-Dist: requests[socks] (>=2.32.4,<3.0.0)
Requires-Dist: scikit-learn (>=1.7.1,<2.0.0)
Requires-Dist: scipy (>=1.15.3,<2.0.0)
Requires-Dist: setuptools (>=80.9.0)
Requires-Dist: tomlkit (>=0.12.2,<0.13.0)
Requires-Dist: tqdm (>=4.66.1,<5.0.0)
Requires-Dist: urllib3 (>=2.6.0,<3.0.0)
Project-URL: Github, https://github.com/hcholab/sfkit
Project-URL: Website, https://sfkit.org/
